{
  "name": "skill_router_autonomous_executor",
  "version": "1.0.0",
  "capabilities": ["complex_automation", "auto_solution_generation", "task_inference"],
  "description": "AionUi Skill Router Bridge. Call this tool when you encounter a task that requires capabilities not currently in your toolset. It will infer, synthesize, and execute a solution automatically.",
  "entrypoint": "python bridge.py",
  "permissions": {
    "network": true,
    "filesystem_read": true,
    "filesystem_write": true,
    "process_exec": true
  }
}